layout_generator/__init__.py
layout_generator/__main__.py
layout_generator/about.py
layout_generator/cli.py
layout_generator/fenics_solver.py
layout_generator/generator.py
layout_generator/generator_c.py
layout_generator/generator_c_power.py
layout_generator/sampler/__init__.py
layout_generator/sampler/continuous/__init__.py
layout_generator/sampler/continuous/base.py
layout_generator/sampler/continuous/config.py
layout_generator/sampler/continuous/gibbs_layout_sampling.py
layout_generator/sampler/continuous/powers_samping.py
layout_generator/sampler/continuous/sequence_layout_sampling.py
layout_generator/sampler/continuous/utils.py
layout_generator/utils/__init__.py
layout_generator/utils/configarg.py
layout_generator/utils/convert.py
layout_generator/utils/default.yml
layout_generator/utils/default3D.yml
layout_generator/utils/default_c.yml
layout_generator/utils/default_c_power.yml
layout_generator/utils/io.py
layout_generator/utils/visualize.py
tests/__init__.py
tests/test_2d.py
tests/test_3d.py
tests/test_about.py
tests/test_cli.py
tests/test_cli_mock.py
tests/test_continuous.py
tests/test_continuous_config.py
tests/test_convert.py
tests/test_generate_c_power.py
tests/test_io.py
layout_generator-0.6.0.dist-info/LICENSE
layout_generator-0.6.0.dist-info/METADATA
layout_generator-0.6.0.dist-info/WHEEL
layout_generator-0.6.0.dist-info/entry_points.txt
layout_generator-0.6.0.dist-info/top_level.txt
layout_generator-0.6.0.dist-info/RECORD
