Metadata-Version: 2.1
Name: layout-generator
Version: 0.6.0
Summary: Layout dataset generator.
Home-page: http://github.com/zweien/layout-generator
Author: Zweien
Author-email: weienzhou@outlook.com
License: LGPL-3.0
Platform: UNKNOWN
Requires-Python: >=3.6
Requires-Dist: tqdm
Requires-Dist: scipy (>=1.0)
Requires-Dist: matplotlib
Requires-Dist: configargparse (>=1.2)
Requires-Dist: pyyaml (>=5.3)
Requires-Dist: h5py
Requires-Dist: fenics
Requires-Dist: black
Provides-Extra: dev
Requires-Dist: pytest (>=3.6) ; extra == 'dev'
Requires-Dist: pytest-shell ; extra == 'dev'
Requires-Dist: pytest-cov ; extra == 'dev'
Requires-Dist: codecov ; extra == 'dev'
Requires-Dist: bump2version ; extra == 'dev'
Provides-Extra: doc
Requires-Dist: sphinx ; extra == 'doc'
Requires-Dist: recommonmark ; extra == 'doc'
Requires-Dist: sphinx-rtd-theme ; extra == 'doc'
